sangreal_bt/__init__.py
sangreal_bt/commons.py
sangreal_bt/datafeed/__init__.py
sangreal_bt/datafeed/datafeed.py
sangreal_bt/strategy/__init__.py
sangreal_bt/strategy/strategy.py
sangreal_bt-0.1.6.dist-info/licenses/LICENSE
sangreal_bt-0.1.6.dist-info/METADATA
sangreal_bt-0.1.6.dist-info/WHEEL
sangreal_bt-0.1.6.dist-info/top_level.txt
sangreal_bt-0.1.6.dist-info/RECORD
