Metadata-Version: 2.4
Name: sangreal_bt
Version: 0.1.6
Summary: A high-performance vector backtesting framework for quantitative strategies
Author-email: liubola <lby3523@gmail.com>
Maintainer-email: liubola <lby3523@gmail.com>
License-Expression: GPL-3.0-or-later
Project-URL: Homepage, https://github.com/liubola/sangreal-bt
Project-URL: Repository, https://github.com/liubola/sangreal-bt
Project-URL: Bug Reports, https://github.com/liubola/sangreal-bt/issues
Project-URL: Documentation, https://github.com/liubola/sangreal-bt/blob/main/README.md
Keywords: backtesting,quantitative,finance,vector,trading,strategy,investment
Classifier: Development Status :: 4 - Beta
Classifier: Intended Audience :: Developers
Classifier: Intended Audience :: Financial and Insurance Industry
Classifier: Intended Audience :: Science/Research
Classifier: Topic :: Office/Business :: Financial
Classifier: Topic :: Scientific/Engineering
Classifier: Topic :: Software Development :: Libraries :: Python Modules
Classifier: Programming Language :: Python :: 3
Classifier: Programming Language :: Python :: 3.6
Classifier: Programming Language :: Python :: 3.7
Classifier: Programming Language :: Python :: 3.8
Classifier: Programming Language :: Python :: 3.9
Classifier: Programming Language :: Python :: 3.10
Classifier: Programming Language :: Python :: 3.11
Classifier: Operating System :: OS Independent
Classifier: Operating System :: POSIX
Classifier: Operating System :: Microsoft :: Windows
Classifier: Operating System :: MacOS
Classifier: Natural Language :: Chinese (Simplified)
Classifier: Natural Language :: English
Requires-Python: >=3.6
License-File: LICENSE
Requires-Dist: attrs>=19.0.0
Requires-Dist: pandas>=1.0.0
Requires-Dist: numpy>=1.18.0
Requires-Dist: addict>=2.2.0
Requires-Dist: python-dateutil>=2.8.0
Provides-Extra: dev
Requires-Dist: pytest>=6.0.0; extra == "dev"
Requires-Dist: pytest-cov>=2.10.0; extra == "dev"
Requires-Dist: black>=21.0.0; extra == "dev"
Requires-Dist: flake8>=3.8.0; extra == "dev"
Requires-Dist: mypy>=0.800; extra == "dev"
Provides-Extra: plotting
Requires-Dist: matplotlib>=3.0.0; extra == "plotting"
Requires-Dist: seaborn>=0.11.0; extra == "plotting"
Provides-Extra: performance
Requires-Dist: numba>=0.50.0; extra == "performance"
Requires-Dist: cython>=0.29.0; extra == "performance"
Dynamic: license-file
